pip_services4_mongodb/__init__.py
pip_services4_mongodb/build/DefaultMongoDbFactory.py
pip_services4_mongodb/build/__init__.py
pip_services4_mongodb/connect/MongoDbConnection.py
pip_services4_mongodb/connect/MongoDbConnectionResolver.py
pip_services4_mongodb/connect/__init__.py
pip_services4_mongodb/persistence/IdentifiableMongoDbPersistence.py
pip_services4_mongodb/persistence/MongoDbIndex.py
pip_services4_mongodb/persistence/MongoDbPersistence.py
pip_services4_mongodb/persistence/__init__.py
pip_services4_mongodb-0.0.1.dist-info/LICENSE
pip_services4_mongodb-0.0.1.dist-info/METADATA
pip_services4_mongodb-0.0.1.dist-info/WHEEL
pip_services4_mongodb-0.0.1.dist-info/top_level.txt
pip_services4_mongodb-0.0.1.dist-info/zip-safe
pip_services4_mongodb-0.0.1.dist-info/RECORD
