Metadata-Version: 2.1
Name: pip-services4-mongodb
Version: 0.0.1
Summary: MongoDb persistence components for Pip.Services in Python
Home-page: http://github.com/pip-services3-python/pip-services4-mongodb-python
Author: Conceptual Vision Consulting LLC
Author-email: seroukhov@gmail.com
License: MIT
Platform: any
Classifier: Intended Audience :: Developers
Classifier: License :: OSI Approved :: MIT License
Classifier: Operating System :: OS Independent
Classifier: Programming Language :: Python
Classifier: Programming Language :: Python :: 3.6
Classifier: Programming Language :: Python :: 3.7
Classifier: Programming Language :: Python :: 3.8
Classifier: Topic :: Software Development :: Libraries :: Python Modules
License-File: LICENSE
Requires-Dist: pymongo <5.0.0,>=4.0.1
Requires-Dist: pip-services4-commons <1.0,>=0.0.1
Requires-Dist: pip-services4-components <1.0,>=0.0.1
Requires-Dist: pip-services4-data <1.0,>=0.0.1
Requires-Dist: pip-services4-persistence <1.0,>=0.0.1
